MANIFEST.in
README.md
setup.cfg
setup.py
feedme/__init__.py
feedme/admin.py
feedme/appconfig.py
feedme/forms.py
feedme/models.py
feedme/urls.py
feedme/utils.py
feedme/views.py
feedme.egg-info/PKG-INFO
feedme.egg-info/SOURCES.txt
feedme.egg-info/dependency_links.txt
feedme.egg-info/top_level.txt
feedme/api/__init__.py
feedme/api/serializers.py
feedme/api/urls.py
feedme/api/validators.py
feedme/api/views.py
feedme/migrations/0001_initial.py
feedme/migrations/0002_auto_20141026_1420.py
feedme/migrations/0003_auto_20141112_2104.py
feedme/migrations/0004_auto_20150203_2036.py
feedme/migrations/0005_auto_20150218_2016.py
feedme/migrations/0006_order_group.py
feedme/migrations/0007_poll_group.py
feedme/migrations/0008_auto_20150428_1659.py
feedme/migrations/0009_auto_20150926_2229.py
feedme/migrations/0010_auto_20151018_1158.py
feedme/migrations/__init__.py
feedme/react/__init__.py
feedme/react/urls.py
feedme/react/views.py
feedme/static/.DS_Store
feedme/static/img/feedme_nyan.gif
feedme/static/js/feedme.min.js
feedme/static/js/feedme/Balance.jsx
feedme/static/js/feedme/Buttons.jsx
feedme/static/js/feedme/IconButton.jsx
feedme/static/js/feedme/Order.jsx
feedme/static/js/feedme/OrderLine.jsx
feedme/static/js/feedme/OrderLineForm.jsx
feedme/static/js/feedme/OrderLineList.jsx
feedme/static/js/feedme/feedme.jsx
feedme/templates/base.html
feedme/templates/messages.html
feedme/templates/feedme/404.html
feedme/templates/feedme/admin.html
feedme/templates/feedme/admin_index.html
feedme/templates/feedme/admin_tabs.html
feedme/templates/feedme/chart.html
feedme/templates/feedme/index.html
feedme/templates/feedme/index_new.html
feedme/templates/feedme/manage_order.html
feedme/templates/feedme/manage_users.html
feedme/templates/feedme/nav.html
feedme/templates/feedme/order_history.html
feedme/templates/feedme/orderview.html
feedme/templates/feedme/poll.html
feedme/templates/feedme/react/groups.html
feedme/templates/feedme/react/index.html
feedme/templatetags/__init__.py
feedme/templatetags/admin_tags.py
feedme/templatetags/css_stuff.py